MANIFEST.in
README.rst
setup.cfg
setup.py
django_royce_bulksms.egg-info/PKG-INFO
django_royce_bulksms.egg-info/SOURCES.txt
django_royce_bulksms.egg-info/dependency_links.txt
django_royce_bulksms.egg-info/requires.txt
django_royce_bulksms.egg-info/top_level.txt
roycebulksms/__init__.py
roycebulksms/admin.py
roycebulksms/apps.py
roycebulksms/forms.py
roycebulksms/models.py
roycebulksms/tests.py
roycebulksms/urls.py
roycebulksms/views.py
roycebulksms/migrations/0001_initial.py
roycebulksms/migrations/0002_contact_senttext.py
roycebulksms/migrations/0003_auto_20220422_1827.py
roycebulksms/migrations/0004_auto_20220422_1830.py
roycebulksms/migrations/0005_auto_20220422_1834.py
roycebulksms/migrations/0006_auto_20220423_2340.py
roycebulksms/migrations/0007_auto_20220425_2230.py
roycebulksms/migrations/__init__.py
roycebulksms/static/css/blog.css
roycebulksms/templates/roycebulksms/apikey.html
roycebulksms/templates/roycebulksms/base.html
roycebulksms/templates/roycebulksms/contacts.html
roycebulksms/templates/roycebulksms/groups.html
roycebulksms/templates/roycebulksms/index.html
roycebulksms/templates/roycebulksms/outbox.html
roycebulksms/templates/roycebulksms/senderid.html
roycebulksms/templates/roycebulksms/sendtocontacts.html
roycebulksms/templates/roycebulksms/sendtogroups.html
roycebulksms/templates/roycebulksms/sendtonumbers.html