Metadata-Version: 2.1
Name: django-royce-bulksms
Version: 1.0
Summary: A Django app to Integrate bulk sms into Django system. It also comes with UI.
Home-page: https://github.com/royceltd/django-royce-bulksms
Author: Royce Ltd
Author-email: developer@roycetechnologies.co.ke
License: BSD-3-Clause  # Example license
Project-URL: Bug Tracker, https://github.com/royceltd/django-royce-bulksms/issues
Platform: UNKNOWN
Classifier: Environment :: Web Environment
Classifier: Framework :: Django
Classifier: Framework :: Django :: 2.0
Classifier: Intended Audience :: Developers
Classifier: License :: OSI Approved :: BSD License
Classifier: Operating System :: OS Independent
Classifier: Programming Language :: Python
Classifier: Programming Language :: Python :: 3
Classifier: Programming Language :: Python :: 3 :: Only
Classifier: Programming Language :: Python :: 3.8
Classifier: Programming Language :: Python :: 3.9
Classifier: Topic :: Internet :: WWW/HTTP
Classifier: Topic :: Internet :: WWW/HTTP :: Dynamic Content
Requires-Python: >=3.6
